openedx_pok/__init__.py
openedx_pok/admin.py
openedx_pok/apps.py
openedx_pok/client.py
openedx_pok/filters.py
openedx_pok/i18n.py
openedx_pok/models.py
openedx_pok/urls.py
openedx_pok/views.py
openedx_pok/migrations/0001_initial.py
openedx_pok/migrations/0002_coursetemplate.py
openedx_pok/migrations/0003_certificatepokapi_custom_parameters_and_more.py
openedx_pok/migrations/0004_rename_course_id_coursetemplate_course.py
openedx_pok/migrations/0005_coursetemplate_emission_type.py
openedx_pok/migrations/0006_coursetemplate_api_key.py
openedx_pok/migrations/0007_remove_coursetemplate_api_key.py
openedx_pok/migrations/0008_alter_coursetemplate_emission_type.py
openedx_pok/migrations/0009_rename_coursetemplate_certificatetemplate_and_more.py
openedx_pok/migrations/0010_alter_certificatetemplate_template_id.py
openedx_pok/migrations/0011_certificatetemplate_page_id_pokcertificate_page.py
openedx_pok/migrations/0012_alter_certificatetemplate_course.py
openedx_pok/migrations/__init__.py
openedx_pok/settings/__init__.py
openedx_pok/settings/common.py
openedx_pok/templates/openedx_pok/certificate_error.html
openedx_pok/templates/openedx_pok/certificate_pok.html
openedx_pok/templates/openedx_pok/certificate_preview.html
openedx_pok/templates/openedx_pok/certificate_processing.html
openedx_pok/utils/__init__.py
openedx_pok-1.0.3.dist-info/licenses/LICENSE.txt
openedx_pok-1.0.3.dist-info/METADATA
openedx_pok-1.0.3.dist-info/WHEEL
openedx_pok-1.0.3.dist-info/entry_points.txt
openedx_pok-1.0.3.dist-info/top_level.txt
openedx_pok-1.0.3.dist-info/RECORD
