Metadata-Version: 2.4
Name: openedx-pok
Version: 1.0.3
Summary: Django plugin for Open edX to manage POK certificates
Home-page: https://github.com/openedx/openedx-pok
Author: aulasneo
Author-email: lberoes@aulasneo.com
Keywords: Python edx
Classifier: Development Status :: 3 - Alpha
Classifier: Framework :: Django
Classifier: Framework :: Django :: 4.2
Classifier: Intended Audience :: Developers
Classifier: License :: Other/Proprietary License
Classifier: Natural Language :: English
Classifier: Programming Language :: Python :: 3
Classifier: Programming Language :: Python :: 3.12
Requires-Python: >=3.11
License-File: LICENSE.txt
Requires-Dist: Django
Requires-Dist: django-model-utils
Requires-Dist: djangorestframework
Requires-Dist: edx-django-utils
Requires-Dist: edx-opaque-keys
Requires-Dist: openedx-atlas
Requires-Dist: requests
Dynamic: author
Dynamic: author-email
Dynamic: classifier
Dynamic: description
Dynamic: description-content-type
Dynamic: home-page
Dynamic: keywords
Dynamic: license-file
Dynamic: requires-dist
Dynamic: requires-python
Dynamic: summary
